{"data":[{"all_awardings":[],"approved_at_utc":null,"approved_by":null,"archived":false,"associated_award":null,"author":"xkumropotash","author_flair_background_color":null,"author_flair_css_class":null,"author_flair_richtext":[],"author_flair_template_id":null,"author_flair_text":null,"author_flair_text_color":null,"author_flair_type":"text","author_fullname":"t2_cdmp51mq","author_is_blocked":false,"author_patreon_flair":false,"author_premium":false,"awarders":[],"banned_at_utc":null,"banned_by":null,"body":"Looks good!","body_html":"&lt;div class=\"md\"&gt;&lt;p&gt;Looks good!&lt;/p&gt;\n&lt;/div&gt;","can_gild":false,"can_mod_post":false,"collapsed":false,"collapsed_because_crowd_control":null,"collapsed_reason":null,"collapsed_reason_code":null,"comment_type":null,"controversiality":0,"created":1728125341.0,"created_utc":1728125341.0,"distinguished":null,"downs":0,"edited":false,"gilded":0,"gildings":{},"id":"lqfrcm7","is_submitter":false,"likes":null,"link_id":"t3_1fssvlt","locked":false,"mod_note":null,"mod_reason_by":null,"mod_reason_title":null,"mod_reports":[],"name":"t1_lqfrcm7","no_follow":true,"num_reports":null,"parent_id":"t3_1fssvlt","permalink":"/r/macapps/comments/1fssvlt/shottr_18_released/lqfrcm7/","removal_reason":null,"replies":"","report_reasons":null,"saved":false,"score":1,"score_hidden":false,"send_replies":true,"stickied":false,"subreddit":"macapps","subreddit_id":"t5_2rt9r","subreddit_name_prefixed":"r/macapps","subreddit_type":"public","top_awarded_type":null,"total_awards_received":0,"treatment_tags":[],"unrepliable_reason":null,"ups":1,"user_reports":[]},{"all_awardings":[],"approved_at_utc":null,"approved_by":null,"archived":false,"associated_award":null,"author":"Golden_Antt","author_flair_background_color":null,"author_flair_css_class":null,"author_flair_richtext":[],"author_flair_template_id":null,"author_flair_text":null,"author_flair_text_color":null,"author_flair_type":"text","author_fullname":"t2_b9cv3u6m","author_is_blocked":false,"author_patreon_flair":false,"author_premium":false,"awarders":[],"banned_at_utc":null,"banned_by":null,"body":"Yeah, a whole 12mb in the background 45mb when in use","body_html":"&lt;div class=\"md\"&gt;&lt;p&gt;Yeah, a whole 12mb in the background 45mb when in use&lt;/p&gt;\n&lt;/div&gt;","can_gild":false,"can_mod_post":false,"collapsed":false,"collapsed_because_crowd_control":null,"collapsed_reason":null,"collapsed_reason_code":null,"comment_type":null,"controversiality":0,"created":1727906181.0,"created_utc":1727906181.0,"distinguished":null,"downs":0,"edited":false,"gilded":0,"gildings":{},"id":"lq1nu7f","is_submitter":false,"likes":null,"link_id":"t3_1fssvlt","locked":false,"mod_note":null,"mod_reason_by":null,"mod_reason_title":null,"mod_reports":[],"name":"t1_lq1nu7f","no_follow":true,"num_reports":null,"parent_id":"t1_lpnkc9u","permalink":"/r/macapps/comments/1fssvlt/shottr_18_released/lq1nu7f/","removal_reason":null,"replies":"","report_reasons":null,"saved":false,"score":1,"score_hidden":false,"send_replies":true,"stickied":false,"subreddit":"macapps","subreddit_id":"t5_2rt9r","subreddit_name_prefixed":"r/macapps","subreddit_type":"public","top_awarded_type":null,"total_awards_received":0,"treatment_tags":[],"unrepliable_reason":null,"ups":1,"user_reports":[]},{"all_awardings":[],"approved_at_utc":null,"approved_by":null,"archived":false,"associated_award":null,"author":"Golden_Antt","author_flair_background_color":null,"author_flair_css_class":null,"author_flair_richtext":[],"author_flair_template_id":null,"author_flair_text":null,"author_flair_text_color":null,"author_flair_type":"text","author_fullname":"t2_b9cv3u6m","author_is_blocked":false,"author_patreon_flair":false,"author_premium":false,"awarders":[],"banned_at_utc":null,"banned_by":null,"body":"For me, the UI is updated but the functionality doesn't work. Nothing happens for either the Backdrop or Custom color button. Same with the \"K\" shortcut.\n\nI downloaded again and replaced the application \u2013 still nothing.","body_html":"&lt;div class=\"md\"&gt;&lt;p&gt;For me, the UI is updated but the functionality doesn&amp;#39;t work. Nothing happens for either the Backdrop or Custom color button. Same with the &amp;quot;K&amp;quot; shortcut.&lt;/p&gt;\n\n&lt;p&gt;I downloaded again and replaced the application \u2013 still nothing.&lt;/p&gt;\n&lt;/div&gt;","can_gild":false,"can_mod_post":false,"collapsed":false,"collapsed_because_crowd_control":null,"collapsed_reason":null,"collapsed_reason_code":null,"comment_type":null,"controversiality":0,"created":1727905504.0,"created_utc":1727905504.0,"distinguished":null,"downs":0,"edited":false,"gilded":0,"gildings":{},"id":"lq1lui3","is_submitter":false,"likes":null,"link_id":"t3_1fssvlt","locked":false,"mod_note":null,"mod_reason_by":null,"mod_reason_title":null,"mod_reports":[],"name":"t1_lq1lui3","no_follow":false,"num_reports":null,"parent_id":"t3_1fssvlt","permalink":"/r/macapps/comments/1fssvlt/shottr_18_released/lq1lui3/","removal_reason":null,"replies":"","report_reasons":null,"saved":false,"score":1,"score_hidden":false,"send_replies":true,"stickied":false,"subreddit":"macapps","subreddit_id":"t5_2rt9r","subreddit_name_prefixed":"r/macapps","subreddit_type":"public","top_awarded_type":null,"total_awards_received":0,"treatment_tags":[],"unrepliable_reason":null,"ups":1,"user_reports":[]},{"all_awardings":[],"approved_at_utc":null,"approved_by":null,"archived":false,"associated_award":null,"author":"jfernandogt","author_flair_background_color":null,"author_flair_css_class":null,"author_flair_richtext":[],"author_flair_template_id":null,"author_flair_text":null,"author_flair_text_color":null,"author_flair_type":"text","author_fullname":"t2_srskf","author_is_blocked":false,"author_patreon_flair":false,"author_premium":false,"awarders":[],"banned_at_utc":null,"banned_by":null,"body":"I couldn't wait for Raycast support, so I created this PR based on the Alfred workflow to add it\n\n[https://github.com/raycast/extensions/pull/14750](https://github.com/raycast/extensions/pull/14750)","body_html":"&lt;div class=\"md\"&gt;&lt;p&gt;I couldn&amp;#39;t wait for Raycast support, so I created this PR based on the Alfred workflow to add it&lt;/p&gt;\n\n&lt;p&gt;&lt;a href=\"https://github.com/raycast/extensions/pull/14750\"&gt;https://github.com/raycast/extensions/pull/14750&lt;/a&gt;&lt;/p&gt;\n&lt;/div&gt;","can_gild":false,"can_mod_post":false,"collapsed":false,"collapsed_because_crowd_control":null,"collapsed_reason":null,"collapsed_reason_code":null,"comment_type":null,"controversiality":0,"created":1727799896.0,"created_utc":1727799896.0,"distinguished":null,"downs":0,"edited":false,"gilded":0,"gildings":{},"id":"lpu0ahg","is_submitter":false,"likes":null,"link_id":"t3_1fssvlt","locked":false,"mod_note":null,"mod_reason_by":null,"mod_reason_title":null,"mod_reports":[],"name":"t1_lpu0ahg","no_follow":true,"num_reports":null,"parent_id":"t3_1fssvlt","permalink":"/r/macapps/comments/1fssvlt/shottr_18_released/lpu0ahg/","removal_reason":null,"replies":"","report_reasons":null,"saved":false,"score":1,"score_hidden":false,"send_replies":true,"stickied":false,"subreddit":"macapps","subreddit_id":"t5_2rt9r","subreddit_name_prefixed":"r/macapps","subreddit_type":"public","top_awarded_type":null,"total_awards_received":0,"treatment_tags":[],"unrepliable_reason":null,"ups":1,"user_reports":[]},{"all_awardings":[],"approved_at_utc":null,"approved_by":null,"archived":false,"associated_award":null,"author":"nez329","author_flair_background_color":null,"author_flair_css_class":null,"author_flair_richtext":[],"author_flair_template_id":null,"author_flair_text":null,"author_flair_text_color":null,"author_flair_type":"text","author_fullname":"t2_438u6s0j","author_is_blocked":false,"author_patreon_flair":false,"author_premium":false,"awarders":[],"banned_at_utc":null,"banned_by":null,"body":"A year ago!\n\nI shall not say further least I incur the wrath of them loyalist.","body_html":"&lt;div class=\"md\"&gt;&lt;p&gt;A year ago!&lt;/p&gt;\n\n&lt;p&gt;I shall not say further least I incur the wrath of them loyalist.&lt;/p&gt;\n&lt;/div&gt;","can_gild":false,"can_mod_post":false,"collapsed":false,"collapsed_because_crowd_control":null,"collapsed_reason":null,"collapsed_reason_code":null,"comment_type":null,"controversiality":0,"created":1727796644.0,"created_utc":1727796644.0,"distinguished":null,"downs":0,"edited":false,"gilded":0,"gildings":{},"id":"lptqd2x","is_submitter":false,"likes":null,"link_id":"t3_1fssvlt","locked":false,"mod_note":null,"mod_reason_by":null,"mod_reason_title":null,"mod_reports":[],"name":"t1_lptqd2x","no_follow":true,"num_reports":null,"parent_id":"t1_lptbyag","permalink":"/r/macapps/comments/1fssvlt/shottr_18_released/lptqd2x/","removal_reason":null,"replies":"","report_reasons":null,"saved":false,"score":1,"score_hidden":false,"send_replies":true,"stickied":false,"subreddit":"macapps","subreddit_id":"t5_2rt9r","subreddit_name_prefixed":"r/macapps","subreddit_type":"public","top_awarded_type":null,"total_awards_received":0,"treatment_tags":[],"unrepliable_reason":null,"ups":1,"user_reports":[]},{"all_awardings":[],"approved_at_utc":null,"approved_by":null,"archived":false,"associated_award":null,"author":"gkavek","author_flair_background_color":null,"author_flair_css_class":null,"author_flair_richtext":[],"author_flair_template_id":null,"author_flair_text":null,"author_flair_text_color":null,"author_flair_type":"text","author_fullname":"t2_vz2pvlov","author_is_blocked":false,"author_patreon_flair":false,"author_premium":false,"awarders":[],"banned_at_utc":null,"banned_by":null,"body":"the website has a section for requesting features. I did post \"rotate feature\" about a year ago.    \nThe development of the app has reduced considerably in the past year. I hope they add the feature sometime.","body_html":"&lt;div class=\"md\"&gt;&lt;p&gt;the website has a section for requesting features. I did post &amp;quot;rotate feature&amp;quot; about a year ago.&lt;br/&gt;\nThe development of the app has reduced considerably in the past year. I hope they add the feature sometime.&lt;/p&gt;\n&lt;/div&gt;","can_gild":false,"can_mod_post":false,"collapsed":false,"collapsed_because_crowd_control":null,"collapsed_reason":null,"collapsed_reason_code":null,"comment_type":null,"controversiality":0,"created":1727791821.0,"created_utc":1727791821.0,"distinguished":null,"downs":0,"edited":false,"gilded":0,"gildings":{},"id":"lptbyag","is_submitter":false,"likes":null,"link_id":"t3_1fssvlt","locked":false,"mod_note":null,"mod_reason_by":null,"mod_reason_title":null,"mod_reports":[],"name":"t1_lptbyag","no_follow":true,"num_reports":null,"parent_id":"t1_lpsiceo","permalink":"/r/macapps/comments/1fssvlt/shottr_18_released/lptbyag/","removal_reason":null,"replies":"","report_reasons":null,"saved":false,"score":1,"score_hidden":false,"send_replies":true,"stickied":false,"subreddit":"macapps","subreddit_id":"t5_2rt9r","subreddit_name_prefixed":"r/macapps","subreddit_type":"public","top_awarded_type":null,"total_awards_received":0,"treatment_tags":[],"unrepliable_reason":null,"ups":1,"user_reports":[]},{"all_awardings":[],"approved_at_utc":null,"approved_by":null,"archived":false,"associated_award":null,"author":"nez329","author_flair_background_color":null,"author_flair_css_class":null,"author_flair_richtext":[],"author_flair_template_id":null,"author_flair_text":null,"author_flair_text_color":null,"author_flair_type":"text","author_fullname":"t2_438u6s0j","author_is_blocked":false,"author_patreon_flair":false,"author_premium":false,"awarders":[],"banned_at_utc":null,"banned_by":null,"body":"I am just stating the facts, albeit bluntly and some of you come at me with \"gnashing teeth and sharpen spears.\n\n\"Wow. Just wow.\n\nShall not compete with loyalist.","body_html":"&lt;div class=\"md\"&gt;&lt;p&gt;I am just stating the facts, albeit bluntly and some of you come at me with &amp;quot;gnashing teeth and sharpen spears.&lt;/p&gt;\n\n&lt;p&gt;&amp;quot;Wow. Just wow.&lt;/p&gt;\n\n&lt;p&gt;Shall not compete with loyalist.&lt;/p&gt;\n&lt;/div&gt;","can_gild":false,"can_mod_post":false,"collapsed":false,"collapsed_because_crowd_control":null,"collapsed_reason":null,"collapsed_reason_code":null,"comment_type":null,"controversiality":0,"created":1727788157.0,"created_utc":1727788157.0,"distinguished":null,"downs":0,"edited":false,"gilded":0,"gildings":{},"id":"lpt204d","is_submitter":false,"likes":null,"link_id":"t3_1fssvlt","locked":false,"mod_note":null,"mod_reason_by":null,"mod_reason_title":null,"mod_reports":[],"name":"t1_lpt204d","no_follow":true,"num_reports":null,"parent_id":"t1_lpn7z22","permalink":"/r/macapps/comments/1fssvlt/shottr_18_released/lpt204d/","removal_reason":null,"replies":"","report_reasons":null,"saved":false,"score":1,"score_hidden":false,"send_replies":true,"stickied":false,"subreddit":"macapps","subreddit_id":"t5_2rt9r","subreddit_name_prefixed":"r/macapps","subreddit_type":"public","top_awarded_type":null,"total_awards_received":0,"treatment_tags":[],"unrepliable_reason":null,"ups":1,"user_reports":[]},{"all_awardings":[],"approved_at_utc":null,"approved_by":null,"archived":false,"associated_award":null,"author":"nez329","author_flair_background_color":null,"author_flair_css_class":null,"author_flair_richtext":[],"author_flair_template_id":null,"author_flair_text":null,"author_flair_text_color":null,"author_flair_type":"text","author_fullname":"t2_438u6s0j","author_is_blocked":false,"author_patreon_flair":false,"author_premium":false,"awarders":[],"banned_at_utc":null,"banned_by":null,"body":"I apologies for being blunt.","body_html":"&lt;div class=\"md\"&gt;&lt;p&gt;I apologies for being blunt.&lt;/p&gt;\n&lt;/div&gt;","can_gild":false,"can_mod_post":false,"collapsed":false,"collapsed_because_crowd_control":null,"collapsed_reason":null,"collapsed_reason_code":null,"comment_type":null,"controversiality":0,"created":1727786504.0,"created_utc":1727786504.0,"distinguished":null,"downs":0,"edited":false,"gilded":0,"gildings":{},"id":"lpsxw5b","is_submitter":false,"likes":null,"link_id":"t3_1fssvlt","locked":false,"mod_note":null,"mod_reason_by":null,"mod_reason_title":null,"mod_reports":[],"name":"t1_lpsxw5b","no_follow":false,"num_reports":null,"parent_id":"t1_lpp2slq","permalink":"/r/macapps/comments/1fssvlt/shottr_18_released/lpsxw5b/","removal_reason":null,"replies":"","report_reasons":null,"saved":false,"score":1,"score_hidden":false,"send_replies":true,"stickied":false,"subreddit":"macapps","subreddit_id":"t5_2rt9r","subreddit_name_prefixed":"r/macapps","subreddit_type":"public","top_awarded_type":null,"total_awards_received":0,"treatment_tags":[],"unrepliable_reason":null,"ups":1,"user_reports":[]},{"all_awardings":[],"approved_at_utc":null,"approved_by":null,"archived":false,"associated_award":null,"author":"nez329","author_flair_background_color":null,"author_flair_css_class":null,"author_flair_richtext":[],"author_flair_template_id":null,"author_flair_text":null,"author_flair_text_color":null,"author_flair_type":"text","author_fullname":"t2_438u6s0j","author_is_blocked":false,"author_patreon_flair":false,"author_premium":false,"awarders":[],"banned_at_utc":null,"banned_by":null,"body":"Yes. I am aware.\n\nJust curious, why no Rotate.","body_html":"&lt;div class=\"md\"&gt;&lt;p&gt;Yes. I am aware.&lt;/p&gt;\n\n&lt;p&gt;Just curious, why no Rotate.&lt;/p&gt;\n&lt;/div&gt;","can_gild":false,"can_mod_post":false,"collapsed":false,"collapsed_because_crowd_control":null,"collapsed_reason":null,"collapsed_reason_code":null,"comment_type":null,"controversiality":0,"created":1727786119.0,"created_utc":1727786119.0,"distinguished":null,"downs":0,"edited":false,"gilded":0,"gildings":{},"id":"lpswzi7","is_submitter":false,"likes":null,"link_id":"t3_1fssvlt","locked":false,"mod_note":null,"mod_reason_by":null,"mod_reason_title":null,"mod_reports":[],"name":"t1_lpswzi7","no_follow":true,"num_reports":null,"parent_id":"t1_lpqq1bo","permalink":"/r/macapps/comments/1fssvlt/shottr_18_released/lpswzi7/","removal_reason":null,"replies":"","report_reasons":null,"saved":false,"score":1,"score_hidden":false,"send_replies":true,"stickied":false,"subreddit":"macapps","subreddit_id":"t5_2rt9r","subreddit_name_prefixed":"r/macapps","subreddit_type":"public","top_awarded_type":null,"total_awards_received":0,"treatment_tags":[],"unrepliable_reason":null,"ups":1,"user_reports":[]},{"all_awardings":[],"approved_at_utc":null,"approved_by":null,"archived":false,"associated_award":null,"author":"nez329","author_flair_background_color":null,"author_flair_css_class":null,"author_flair_richtext":[],"author_flair_template_id":null,"author_flair_text":null,"author_flair_text_color":null,"author_flair_type":"text","author_fullname":"t2_438u6s0j","author_is_blocked":false,"author_patreon_flair":false,"author_premium":false,"awarders":[],"banned_at_utc":null,"banned_by":null,"body":"Yes. However, the flow is to add text to the screenshot after it has been rotated.\n\nAnd yes, I can screenshot first, save. Reopen in preview then markup.\n\nSo why I need Shottr again?","body_html":"&lt;div class=\"md\"&gt;&lt;p&gt;Yes. However, the flow is to add text to the screenshot after it has been rotated.&lt;/p&gt;\n\n&lt;p&gt;And yes, I can screenshot first, save. Reopen in preview then markup.&lt;/p&gt;\n\n&lt;p&gt;So why I need Shottr again?&lt;/p&gt;\n&lt;/div&gt;","can_gild":false,"can_mod_post":false,"collapsed":false,"collapsed_because_crowd_control":null,"collapsed_reason":null,"collapsed_reason_code":null,"comment_type":null,"controversiality":0,"created":1727786025.0,"created_utc":1727786025.0,"distinguished":null,"downs":0,"edited":false,"gilded":0,"gildings":{},"id":"lpswrlp","is_submitter":false,"likes":null,"link_id":"t3_1fssvlt","locked":false,"mod_note":null,"mod_reason_by":null,"mod_reason_title":null,"mod_reports":[],"name":"t1_lpswrlp","no_follow":true,"num_reports":null,"parent_id":"t1_lpp0o2b","permalink":"/r/macapps/comments/1fssvlt/shottr_18_released/lpswrlp/","removal_reason":null,"replies":"","report_reasons":null,"saved":false,"score":1,"score_hidden":false,"send_replies":true,"stickied":false,"subreddit":"macapps","subreddit_id":"t5_2rt9r","subreddit_name_prefixed":"r/macapps","subreddit_type":"public","top_awarded_type":null,"total_awards_received":0,"treatment_tags":[],"unrepliable_reason":null,"ups":1,"user_reports":[]},{"all_awardings":[],"approved_at_utc":null,"approved_by":null,"archived":false,"associated_award":null,"author":"reDzikpr0","author_flair_background_color":null,"author_flair_css_class":null,"author_flair_richtext":[],"author_flair_template_id":null,"author_flair_text":null,"author_flair_text_color":null,"author_flair_type":"text","author_fullname":"t2_i606nc53","author_is_blocked":false,"author_patreon_flair":false,"author_premium":false,"awarders":[],"banned_at_utc":null,"banned_by":null,"body":"write to the developer it is unlikely to be a problem to add this feature","body_html":"&lt;div class=\"md\"&gt;&lt;p&gt;write to the developer it is unlikely to be a problem to add this feature&lt;/p&gt;\n&lt;/div&gt;","can_gild":false,"can_mod_post":false,"collapsed":false,"collapsed_because_crowd_control":null,"collapsed_reason":null,"collapsed_reason_code":null,"comment_type":null,"controversiality":0,"created":1727778815.0,"created_utc":1727778815.0,"distinguished":null,"downs":0,"edited":false,"gilded":0,"gildings":{},"id":"lpsiceo","is_submitter":false,"likes":null,"link_id":"t3_1fssvlt","locked":false,"mod_note":null,"mod_reason_by":null,"mod_reason_title":null,"mod_reports":[],"name":"t1_lpsiceo","no_follow":false,"num_reports":null,"parent_id":"t1_lpouyd7","permalink":"/r/macapps/comments/1fssvlt/shottr_18_released/lpsiceo/","removal_reason":null,"replies":"","report_reasons":null,"saved":false,"score":1,"score_hidden":false,"send_replies":true,"stickied":false,"subreddit":"macapps","subreddit_id":"t5_2rt9r","subreddit_name_prefixed":"r/macapps","subreddit_type":"public","top_awarded_type":null,"total_awards_received":0,"treatment_tags":[],"unrepliable_reason":null,"ups":1,"user_reports":[]},{"all_awardings":[],"approved_at_utc":null,"approved_by":null,"archived":false,"associated_award":null,"author":"boxcreate","author_flair_background_color":null,"author_flair_css_class":null,"author_flair_richtext":[],"author_flair_template_id":null,"author_flair_text":null,"author_flair_text_color":null,"author_flair_type":"text","author_fullname":"t2_ia2p5lbg","author_is_blocked":false,"author_patreon_flair":false,"author_premium":false,"awarders":[],"banned_at_utc":null,"banned_by":null,"body":"Love the Alfred implementation!","body_html":"&lt;div class=\"md\"&gt;&lt;p&gt;Love the Alfred implementation!&lt;/p&gt;\n&lt;/div&gt;","can_gild":false,"can_mod_post":false,"collapsed":false,"collapsed_because_crowd_control":null,"collapsed_reason":null,"collapsed_reason_code":null,"comment_type":null,"controversiality":0,"created":1727755305.0,"created_utc":1727755305.0,"distinguished":null,"downs":0,"edited":false,"gilded":0,"gildings":{},"id":"lprhde5","is_submitter":false,"likes":null,"link_id":"t3_1fssvlt","locked":false,"mod_note":null,"mod_reason_by":null,"mod_reason_title":null,"mod_reports":[],"name":"t1_lprhde5","no_follow":true,"num_reports":null,"parent_id":"t3_1fssvlt","permalink":"/r/macapps/comments/1fssvlt/shottr_18_released/lprhde5/","removal_reason":null,"replies":"","report_reasons":null,"saved":false,"score":1,"score_hidden":false,"send_replies":true,"stickied":false,"subreddit":"macapps","subreddit_id":"t5_2rt9r","subreddit_name_prefixed":"r/macapps","subreddit_type":"public","top_awarded_type":null,"total_awards_received":0,"treatment_tags":[],"unrepliable_reason":null,"ups":1,"user_reports":[]},{"all_awardings":[],"approved_at_utc":null,"approved_by":null,"archived":false,"associated_award":null,"author":"johnmcboston","author_flair_background_color":null,"author_flair_css_class":null,"author_flair_richtext":[],"author_flair_template_id":null,"author_flair_text":null,"author_flair_text_color":null,"author_flair_type":"text","author_fullname":"t2_begbweq","author_is_blocked":false,"author_patreon_flair":false,"author_premium":false,"awarders":[],"banned_at_utc":null,"banned_by":null,"body":"App question while we're here.   Is it normal that the thumbnail is so tiny while the editor version is big enough to read?","body_html":"&lt;div class=\"md\"&gt;&lt;p&gt;App question while we&amp;#39;re here.   Is it normal that the thumbnail is so tiny while the editor version is big enough to read?&lt;/p&gt;\n&lt;/div&gt;","can_gild":false,"can_mod_post":false,"collapsed":false,"collapsed_because_crowd_control":null,"collapsed_reason":null,"collapsed_reason_code":null,"comment_type":null,"controversiality":0,"created":1727747873.0,"created_utc":1727747873.0,"distinguished":null,"downs":0,"edited":false,"gilded":0,"gildings":{},"id":"lpqz0sl","is_submitter":false,"likes":null,"link_id":"t3_1fssvlt","locked":false,"mod_note":null,"mod_reason_by":null,"mod_reason_title":null,"mod_reports":[],"name":"t1_lpqz0sl","no_follow":true,"num_reports":null,"parent_id":"t3_1fssvlt","permalink":"/r/macapps/comments/1fssvlt/shottr_18_released/lpqz0sl/","removal_reason":null,"replies":"","report_reasons":null,"saved":false,"score":1,"score_hidden":false,"send_replies":true,"stickied":false,"subreddit":"macapps","subreddit_id":"t5_2rt9r","subreddit_name_prefixed":"r/macapps","subreddit_type":"public","top_awarded_type":null,"total_awards_received":0,"treatment_tags":[],"unrepliable_reason":null,"ups":1,"user_reports":[]},{"all_awardings":[],"approved_at_utc":null,"approved_by":null,"archived":false,"associated_award":null,"author":"0x080","author_flair_background_color":null,"author_flair_css_class":null,"author_flair_richtext":[],"author_flair_template_id":null,"author_flair_text":null,"author_flair_text_color":null,"author_flair_type":"text","author_fullname":"t2_xcseug94a","author_is_blocked":false,"author_patreon_flair":false,"author_premium":false,"awarders":[],"banned_at_utc":null,"banned_by":null,"body":"You can even rotate an image right in finder preview window lmao","body_html":"&lt;div class=\"md\"&gt;&lt;p&gt;You can even rotate an image right in finder preview window lmao&lt;/p&gt;\n&lt;/div&gt;","can_gild":false,"can_mod_post":false,"collapsed":false,"collapsed_because_crowd_control":null,"collapsed_reason":null,"collapsed_reason_code":null,"comment_type":null,"controversiality":0,"created":1727744516.0,"created_utc":1727744516.0,"distinguished":null,"downs":0,"edited":false,"gilded":0,"gildings":{},"id":"lpqq1bo","is_submitter":false,"likes":null,"link_id":"t3_1fssvlt","locked":false,"mod_note":null,"mod_reason_by":null,"mod_reason_title":null,"mod_reports":[],"name":"t1_lpqq1bo","no_follow":true,"num_reports":null,"parent_id":"t1_lpp0o2b","permalink":"/r/macapps/comments/1fssvlt/shottr_18_released/lpqq1bo/","removal_reason":null,"replies":"","report_reasons":null,"saved":false,"score":1,"score_hidden":false,"send_replies":true,"stickied":false,"subreddit":"macapps","subreddit_id":"t5_2rt9r","subreddit_name_prefixed":"r/macapps","subreddit_type":"public","top_awarded_type":null,"total_awards_received":0,"treatment_tags":[],"unrepliable_reason":null,"ups":1,"user_reports":[]},{"all_awardings":[],"approved_at_utc":null,"approved_by":null,"archived":false,"associated_award":null,"author":"geoken","author_flair_background_color":null,"author_flair_css_class":null,"author_flair_richtext":[],"author_flair_template_id":null,"author_flair_text":null,"author_flair_text_color":null,"author_flair_type":"text","author_fullname":"t2_35x7f","author_is_blocked":false,"author_patreon_flair":false,"author_premium":false,"awarders":[],"banned_at_utc":null,"banned_by":null,"body":"I updated it because I got an email this morning about the update. In the email, it\u2019s says you can use the link to manually update now - or wait a few days and it will auto update.","body_html":"&lt;div class=\"md\"&gt;&lt;p&gt;I updated it because I got an email this morning about the update. In the email, it\u2019s says you can use the link to manually update now - or wait a few days and it will auto update.&lt;/p&gt;\n&lt;/div&gt;","can_gild":false,"can_mod_post":false,"collapsed":false,"collapsed_because_crowd_control":null,"collapsed_reason":null,"collapsed_reason_code":null,"comment_type":null,"controversiality":0,"created":1727734727.0,"created_utc":1727734727.0,"distinguished":null,"downs":0,"edited":false,"gilded":0,"gildings":{},"id":"lppz9pk","is_submitter":false,"likes":null,"link_id":"t3_1fssvlt","locked":false,"mod_note":null,"mod_reason_by":null,"mod_reason_title":null,"mod_reports":[],"name":"t1_lppz9pk","no_follow":true,"num_reports":null,"parent_id":"t1_lpnb2kh","permalink":"/r/macapps/comments/1fssvlt/shottr_18_released/lppz9pk/","removal_reason":null,"replies":"","report_reasons":null,"saved":false,"score":1,"score_hidden":false,"send_replies":true,"stickied":false,"subreddit":"macapps","subreddit_id":"t5_2rt9r","subreddit_name_prefixed":"r/macapps","subreddit_type":"public","top_awarded_type":null,"total_awards_received":0,"treatment_tags":[],"unrepliable_reason":null,"ups":1,"user_reports":[]},{"all_awardings":[],"approved_at_utc":null,"approved_by":null,"archived":false,"associated_award":null,"author":"Romachamp10","author_flair_background_color":null,"author_flair_css_class":null,"author_flair_richtext":[],"author_flair_template_id":null,"author_flair_text":null,"author_flair_text_color":null,"author_flair_type":"text","author_fullname":"t2_vpb0cu3bl","author_is_blocked":false,"author_patreon_flair":false,"author_premium":false,"awarders":[],"banned_at_utc":null,"banned_by":null,"body":"I would like the developer to make the UI feel more minimalistic and similar to Apple\u2019s UI. The main competitor CleanShot made just this, but this one has potential to be even better, if it had such a UI, though it\u2019s more about the taste.","body_html":"&lt;div class=\"md\"&gt;&lt;p&gt;I would like the developer to make the UI feel more minimalistic and similar to Apple\u2019s UI. The main competitor CleanShot made just this, but this one has potential to be even better, if it had such a UI, though it\u2019s more about the taste.&lt;/p&gt;\n&lt;/div&gt;","can_gild":false,"can_mod_post":false,"collapsed":false,"collapsed_because_crowd_control":null,"collapsed_reason":null,"collapsed_reason_code":null,"comment_type":null,"controversiality":0,"created":1727726060.0,"created_utc":1727726060.0,"distinguished":null,"downs":0,"edited":false,"gilded":0,"gildings":{},"id":"lpp95f1","is_submitter":false,"likes":null,"link_id":"t3_1fssvlt","locked":false,"mod_note":null,"mod_reason_by":null,"mod_reason_title":null,"mod_reports":[],"name":"t1_lpp95f1","no_follow":true,"num_reports":null,"parent_id":"t3_1fssvlt","permalink":"/r/macapps/comments/1fssvlt/shottr_18_released/lpp95f1/","removal_reason":null,"replies":"","report_reasons":null,"saved":false,"score":1,"score_hidden":false,"send_replies":true,"stickied":false,"subreddit":"macapps","subreddit_id":"t5_2rt9r","subreddit_name_prefixed":"r/macapps","subreddit_type":"public","top_awarded_type":null,"total_awards_received":0,"treatment_tags":[],"unrepliable_reason":null,"ups":1,"user_reports":[]},{"all_awardings":[],"approved_at_utc":null,"approved_by":null,"archived":false,"associated_award":null,"author":"amerpie","author_flair_background_color":null,"author_flair_css_class":null,"author_flair_richtext":[],"author_flair_template_id":null,"author_flair_text":null,"author_flair_text_color":null,"author_flair_type":"text","author_fullname":"t2_2xbm","author_is_blocked":false,"author_patreon_flair":false,"author_premium":true,"awarders":[],"banned_at_utc":null,"banned_by":null,"body":"Thanks. That makes a lot more sense than \"because I need to\".","body_html":"&lt;div class=\"md\"&gt;&lt;p&gt;Thanks. That makes a lot more sense than &amp;quot;because I need to&amp;quot;.&lt;/p&gt;\n&lt;/div&gt;","can_gild":false,"can_mod_post":false,"collapsed":false,"collapsed_because_crowd_control":null,"collapsed_reason":null,"collapsed_reason_code":null,"comment_type":null,"controversiality":0,"created":1727724096.0,"created_utc":1727724096.0,"distinguished":null,"downs":0,"edited":false,"gilded":0,"gildings":{},"id":"lpp2slq","is_submitter":true,"likes":null,"link_id":"t3_1fssvlt","locked":false,"mod_note":null,"mod_reason_by":null,"mod_reason_title":null,"mod_reports":[],"name":"t1_lpp2slq","no_follow":true,"num_reports":null,"parent_id":"t1_lpouyd7","permalink":"/r/macapps/comments/1fssvlt/shottr_18_released/lpp2slq/","removal_reason":null,"replies":"","report_reasons":null,"saved":false,"score":1,"score_hidden":false,"send_replies":true,"stickied":false,"subreddit":"macapps","subreddit_id":"t5_2rt9r","subreddit_name_prefixed":"r/macapps","subreddit_type":"public","top_awarded_type":null,"total_awards_received":0,"treatment_tags":[],"unrepliable_reason":null,"ups":1,"user_reports":[]},{"all_awardings":[],"approved_at_utc":null,"approved_by":null,"archived":false,"associated_award":null,"author":"Decaf_GT","author_flair_background_color":null,"author_flair_css_class":null,"author_flair_richtext":[],"author_flair_template_id":null,"author_flair_text":null,"author_flair_text_color":null,"author_flair_type":"text","author_fullname":"t2_r98e1eogc","author_is_blocked":false,"author_patreon_flair":false,"author_premium":false,"awarders":[],"banned_at_utc":null,"banned_by":null,"body":"You know you can just open the screenshot in your preferred viewer and rotate it there, right? \n\nRotation is an image editing and image preview function, not a screenshot and screenshot annotation function.","body_html":"&lt;div class=\"md\"&gt;&lt;p&gt;You know you can just open the screenshot in your preferred viewer and rotate it there, right? &lt;/p&gt;\n\n&lt;p&gt;Rotation is an image editing and image preview function, not a screenshot and screenshot annotation function.&lt;/p&gt;\n&lt;/div&gt;","can_gild":false,"can_mod_post":false,"collapsed":false,"collapsed_because_crowd_control":null,"collapsed_reason":null,"collapsed_reason_code":null,"comment_type":null,"controversiality":0,"created":1727723433.0,"created_utc":1727723433.0,"distinguished":null,"downs":0,"edited":false,"gilded":0,"gildings":{},"id":"lpp0o2b","is_submitter":false,"likes":null,"link_id":"t3_1fssvlt","locked":false,"mod_note":null,"mod_reason_by":null,"mod_reason_title":null,"mod_reports":[],"name":"t1_lpp0o2b","no_follow":true,"num_reports":null,"parent_id":"t1_lpn9amd","permalink":"/r/macapps/comments/1fssvlt/shottr_18_released/lpp0o2b/","removal_reason":null,"replies":"","report_reasons":null,"saved":false,"score":1,"score_hidden":false,"send_replies":true,"stickied":false,"subreddit":"macapps","subreddit_id":"t5_2rt9r","subreddit_name_prefixed":"r/macapps","subreddit_type":"public","top_awarded_type":null,"total_awards_received":0,"treatment_tags":[],"unrepliable_reason":null,"ups":1,"user_reports":[]},{"all_awardings":[],"approved_at_utc":null,"approved_by":null,"archived":false,"associated_award":null,"author":"Decaf_GT","author_flair_background_color":null,"author_flair_css_class":null,"author_flair_richtext":[],"author_flair_template_id":null,"author_flair_text":null,"author_flair_text_color":null,"author_flair_type":"text","author_fullname":"t2_r98e1eogc","author_is_blocked":false,"author_patreon_flair":false,"author_premium":false,"awarders":[],"banned_at_utc":null,"banned_by":null,"body":"Lovely addition to a great tool. I use CleanShot X now but I bought Shottr to support the dev, great work :)","body_html":"&lt;div class=\"md\"&gt;&lt;p&gt;Lovely addition to a great tool. I use CleanShot X now but I bought Shottr to support the dev, great work :)&lt;/p&gt;\n&lt;/div&gt;","can_gild":false,"can_mod_post":false,"collapsed":false,"collapsed_because_crowd_control":null,"collapsed_reason":null,"collapsed_reason_code":null,"comment_type":null,"controversiality":0,"created":1727723347.0,"created_utc":1727723347.0,"distinguished":null,"downs":0,"edited":false,"gilded":0,"gildings":{},"id":"lpp0e5k","is_submitter":false,"likes":null,"link_id":"t3_1fssvlt","locked":false,"mod_note":null,"mod_reason_by":null,"mod_reason_title":null,"mod_reports":[],"name":"t1_lpp0e5k","no_follow":true,"num_reports":null,"parent_id":"t3_1fssvlt","permalink":"/r/macapps/comments/1fssvlt/shottr_18_released/lpp0e5k/","removal_reason":null,"replies":"","report_reasons":null,"saved":false,"score":1,"score_hidden":false,"send_replies":true,"stickied":false,"subreddit":"macapps","subreddit_id":"t5_2rt9r","subreddit_name_prefixed":"r/macapps","subreddit_type":"public","top_awarded_type":null,"total_awards_received":0,"treatment_tags":[],"unrepliable_reason":null,"ups":1,"user_reports":[]},{"all_awardings":[],"approved_at_utc":null,"approved_by":null,"archived":false,"associated_award":null,"author":"gkavek","author_flair_background_color":null,"author_flair_css_class":null,"author_flair_richtext":[],"author_flair_template_id":null,"author_flair_text":null,"author_flair_text_color":null,"author_flair_type":"text","author_fullname":"t2_vz2pvlov","author_is_blocked":false,"author_patreon_flair":false,"author_premium":false,"awarders":[],"banned_at_utc":null,"banned_by":null,"body":"I use the web or desktop version of apps like whatsapp and signal. Often I get sent images or mobile device screenshots that were taken in landscape mode and I need to point something out on them. In these cases I usually screenshot them and use markup to point what is required. In these cases, rotate would be very useful. It would avoid the need to have to ask them to resend in portrait.","body_html":"&lt;div class=\"md\"&gt;&lt;p&gt;I use the web or desktop version of apps like whatsapp and signal. Often I get sent images or mobile device screenshots that were taken in landscape mode and I need to point something out on them. In these cases I usually screenshot them and use markup to point what is required. In these cases, rotate would be very useful. It would avoid the need to have to ask them to resend in portrait.&lt;/p&gt;\n&lt;/div&gt;","can_gild":false,"can_mod_post":false,"collapsed":false,"collapsed_because_crowd_control":null,"collapsed_reason":null,"collapsed_reason_code":null,"comment_type":null,"controversiality":0,"created":1727721633.0,"created_utc":1727721633.0,"distinguished":null,"downs":0,"edited":false,"gilded":0,"gildings":{},"id":"lpouyd7","is_submitter":false,"likes":null,"link_id":"t3_1fssvlt","locked":false,"mod_note":null,"mod_reason_by":null,"mod_reason_title":null,"mod_reports":[],"name":"t1_lpouyd7","no_follow":true,"num_reports":null,"parent_id":"t1_lpn8kbn","permalink":"/r/macapps/comments/1fssvlt/shottr_18_released/lpouyd7/","removal_reason":null,"replies":"","report_reasons":null,"saved":false,"score":1,"score_hidden":false,"send_replies":true,"stickied":false,"subreddit":"macapps","subreddit_id":"t5_2rt9r","subreddit_name_prefixed":"r/macapps","subreddit_type":"public","top_awarded_type":null,"total_awards_received":0,"treatment_tags":[],"unrepliable_reason":null,"ups":1,"user_reports":[]},{"all_awardings":[],"approved_at_utc":null,"approved_by":null,"archived":false,"associated_award":null,"author":"mikepictor","author_flair_background_color":null,"author_flair_css_class":null,"author_flair_richtext":[],"author_flair_template_id":null,"author_flair_text":null,"author_flair_text_color":null,"author_flair_type":"text","author_fullname":"t2_68xr9","author_is_blocked":false,"author_patreon_flair":false,"author_premium":false,"awarders":[],"banned_at_utc":null,"banned_by":null,"body":"it says the extension is \"coming soon\", this version just adds support for it.","body_html":"&lt;div class=\"md\"&gt;&lt;p&gt;it says the extension is &amp;quot;coming soon&amp;quot;, this version just adds support for it.&lt;/p&gt;\n&lt;/div&gt;","can_gild":false,"can_mod_post":false,"collapsed":false,"collapsed_because_crowd_control":null,"collapsed_reason":null,"collapsed_reason_code":null,"comment_type":null,"controversiality":0,"created":1727714559.0,"created_utc":1727714559.0,"distinguished":null,"downs":0,"edited":false,"gilded":0,"gildings":{},"id":"lpo8mcn","is_submitter":false,"likes":null,"link_id":"t3_1fssvlt","locked":false,"mod_note":null,"mod_reason_by":null,"mod_reason_title":null,"mod_reports":[],"name":"t1_lpo8mcn","no_follow":true,"num_reports":null,"parent_id":"t1_lpnyevw","permalink":"/r/macapps/comments/1fssvlt/shottr_18_released/lpo8mcn/","removal_reason":null,"replies":"","report_reasons":null,"saved":false,"score":1,"score_hidden":false,"send_replies":true,"stickied":false,"subreddit":"macapps","subreddit_id":"t5_2rt9r","subreddit_name_prefixed":"r/macapps","subreddit_type":"public","top_awarded_type":null,"total_awards_received":0,"treatment_tags":[],"unrepliable_reason":null,"ups":1,"user_reports":[]},{"all_awardings":[],"approved_at_utc":null,"approved_by":null,"archived":false,"associated_award":null,"author":"raaamyaraaavan","author_flair_background_color":null,"author_flair_css_class":null,"author_flair_richtext":[],"author_flair_template_id":null,"author_flair_text":null,"author_flair_text_color":null,"author_flair_type":"text","author_fullname":"t2_g0tx64e3","author_is_blocked":false,"author_patreon_flair":false,"author_premium":false,"awarders":[],"banned_at_utc":null,"banned_by":null,"body":"Use the deep link from shottr doc to create app links in raycast. No extension required.","body_html":"&lt;div class=\"md\"&gt;&lt;p&gt;Use the deep link from shottr doc to create app links in raycast. No extension required.&lt;/p&gt;\n&lt;/div&gt;","can_gild":false,"can_mod_post":false,"collapsed":false,"collapsed_because_crowd_control":null,"collapsed_reason":null,"collapsed_reason_code":null,"comment_type":null,"controversiality":0,"created":1727713105.0,"created_utc":1727713105.0,"distinguished":null,"downs":0,"edited":false,"gilded":0,"gildings":{},"id":"lpo44mh","is_submitter":false,"likes":null,"link_id":"t3_1fssvlt","locked":false,"mod_note":null,"mod_reason_by":null,"mod_reason_title":null,"mod_reports":[],"name":"t1_lpo44mh","no_follow":true,"num_reports":null,"parent_id":"t1_lpnyevw","permalink":"/r/macapps/comments/1fssvlt/shottr_18_released/lpo44mh/","removal_reason":null,"replies":"","report_reasons":null,"saved":false,"score":1,"score_hidden":false,"send_replies":true,"stickied":false,"subreddit":"macapps","subreddit_id":"t5_2rt9r","subreddit_name_prefixed":"r/macapps","subreddit_type":"public","top_awarded_type":null,"total_awards_received":0,"treatment_tags":[],"unrepliable_reason":null,"ups":1,"user_reports":[]},{"all_awardings":[],"approved_at_utc":null,"approved_by":null,"archived":false,"associated_award":null,"author":"dokte","author_flair_background_color":null,"author_flair_css_class":null,"author_flair_richtext":[],"author_flair_template_id":null,"author_flair_text":null,"author_flair_text_color":null,"author_flair_type":"text","author_fullname":"t2_47hdi","author_is_blocked":false,"author_patreon_flair":false,"author_premium":false,"awarders":[],"banned_at_utc":null,"banned_by":null,"body":"I can't find the Raycast extension it mentions, can you?","body_html":"&lt;div class=\"md\"&gt;&lt;p&gt;I can&amp;#39;t find the Raycast extension it mentions, can you?&lt;/p&gt;\n&lt;/div&gt;","can_gild":false,"can_mod_post":false,"collapsed":false,"collapsed_because_crowd_control":null,"collapsed_reason":null,"collapsed_reason_code":null,"comment_type":null,"controversiality":0,"created":1727711243.0,"created_utc":1727711243.0,"distinguished":null,"downs":0,"edited":false,"gilded":0,"gildings":{},"id":"lpnyevw","is_submitter":false,"likes":null,"link_id":"t3_1fssvlt","locked":false,"mod_note":null,"mod_reason_by":null,"mod_reason_title":null,"mod_reports":[],"name":"t1_lpnyevw","no_follow":true,"num_reports":null,"parent_id":"t1_lpnodcu","permalink":"/r/macapps/comments/1fssvlt/shottr_18_released/lpnyevw/","removal_reason":null,"replies":"","report_reasons":null,"saved":false,"score":1,"score_hidden":false,"send_replies":true,"stickied":false,"subreddit":"macapps","subreddit_id":"t5_2rt9r","subreddit_name_prefixed":"r/macapps","subreddit_type":"public","top_awarded_type":null,"total_awards_received":0,"treatment_tags":[],"unrepliable_reason":null,"ups":1,"user_reports":[]},{"all_awardings":[],"approved_at_utc":null,"approved_by":null,"archived":false,"associated_award":null,"author":"chromatophoreskin","author_flair_background_color":null,"author_flair_css_class":null,"author_flair_richtext":[],"author_flair_template_id":null,"author_flair_text":null,"author_flair_text_color":null,"author_flair_type":"text","author_fullname":"t2_17hmkz","author_is_blocked":false,"author_patreon_flair":false,"author_premium":false,"awarders":[],"banned_at_utc":null,"banned_by":null,"body":"Shottr is on homebrew. The update isn't there yet but it should be soon.","body_html":"&lt;div class=\"md\"&gt;&lt;p&gt;Shottr is on homebrew. The update isn&amp;#39;t there yet but it should be soon.&lt;/p&gt;\n&lt;/div&gt;","can_gild":false,"can_mod_post":false,"collapsed":false,"collapsed_because_crowd_control":null,"collapsed_reason":null,"collapsed_reason_code":null,"comment_type":null,"controversiality":0,"created":1727711233.0,"created_utc":1727711233.0,"distinguished":null,"downs":0,"edited":false,"gilded":0,"gildings":{},"id":"lpnydun","is_submitter":false,"likes":null,"link_id":"t3_1fssvlt","locked":false,"mod_note":null,"mod_reason_by":null,"mod_reason_title":null,"mod_reports":[],"name":"t1_lpnydun","no_follow":true,"num_reports":null,"parent_id":"t1_lpmtaix","permalink":"/r/macapps/comments/1fssvlt/shottr_18_released/lpnydun/","removal_reason":null,"replies":"","report_reasons":null,"saved":false,"score":1,"score_hidden":false,"send_replies":true,"stickied":false,"subreddit":"macapps","subreddit_id":"t5_2rt9r","subreddit_name_prefixed":"r/macapps","subreddit_type":"public","top_awarded_type":null,"total_awards_received":0,"treatment_tags":[],"unrepliable_reason":null,"ups":1,"user_reports":[]},{"all_awardings":[],"approved_at_utc":null,"approved_by":null,"archived":false,"associated_award":null,"author":"mikepictor","author_flair_background_color":null,"author_flair_css_class":null,"author_flair_richtext":[],"author_flair_template_id":null,"author_flair_text":null,"author_flair_text_color":null,"author_flair_type":"text","author_fullname":"t2_68xr9","author_is_blocked":false,"author_patreon_flair":false,"author_premium":false,"awarders":[],"banned_at_utc":null,"banned_by":null,"body":"OMG Raycast support, that has some promise","body_html":"&lt;div class=\"md\"&gt;&lt;p&gt;OMG Raycast support, that has some promise&lt;/p&gt;\n&lt;/div&gt;","can_gild":false,"can_mod_post":false,"collapsed":false,"collapsed_because_crowd_control":null,"collapsed_reason":null,"collapsed_reason_code":null,"comment_type":null,"controversiality":0,"created":1727707912.0,"created_utc":1727707912.0,"distinguished":null,"downs":0,"edited":false,"gilded":0,"gildings":{},"id":"lpnodcu","is_submitter":false,"likes":null,"link_id":"t3_1fssvlt","locked":false,"mod_note":null,"mod_reason_by":null,"mod_reason_title":null,"mod_reports":[],"name":"t1_lpnodcu","no_follow":true,"num_reports":null,"parent_id":"t3_1fssvlt","permalink":"/r/macapps/comments/1fssvlt/shottr_18_released/lpnodcu/","removal_reason":null,"replies":"","report_reasons":null,"saved":false,"score":1,"score_hidden":false,"send_replies":true,"stickied":false,"subreddit":"macapps","subreddit_id":"t5_2rt9r","subreddit_name_prefixed":"r/macapps","subreddit_type":"public","top_awarded_type":null,"total_awards_received":0,"treatment_tags":[],"unrepliable_reason":null,"ups":1,"user_reports":[]},{"all_awardings":[],"approved_at_utc":null,"approved_by":null,"archived":false,"associated_award":null,"author":"mikepictor","author_flair_background_color":null,"author_flair_css_class":null,"author_flair_richtext":[],"author_flair_template_id":null,"author_flair_text":null,"author_flair_text_color":null,"author_flair_type":"text","author_fullname":"t2_68xr9","author_is_blocked":false,"author_patreon_flair":false,"author_premium":false,"awarders":[],"banned_at_utc":null,"banned_by":null,"body":"I am not sure I have ever used a screenshot tool with a rotate option. Don't act like this is a bog standard tool anyone might expect. You can send the creator a feature request.","body_html":"&lt;div class=\"md\"&gt;&lt;p&gt;I am not sure I have ever used a screenshot tool with a rotate option. Don&amp;#39;t act like this is a bog standard tool anyone might expect. You can send the creator a feature request.&lt;/p&gt;\n&lt;/div&gt;","can_gild":false,"can_mod_post":false,"collapsed":false,"collapsed_because_crowd_control":null,"collapsed_reason":null,"collapsed_reason_code":null,"comment_type":null,"controversiality":0,"created":1727707888.0,"created_utc":1727707888.0,"distinguished":null,"downs":0,"edited":false,"gilded":0,"gildings":{},"id":"lpnoaou","is_submitter":false,"likes":null,"link_id":"t3_1fssvlt","locked":false,"mod_note":null,"mod_reason_by":null,"mod_reason_title":null,"mod_reports":[],"name":"t1_lpnoaou","no_follow":false,"num_reports":null,"parent_id":"t1_lpn9amd","permalink":"/r/macapps/comments/1fssvlt/shottr_18_released/lpnoaou/","removal_reason":null,"replies":"","report_reasons":null,"saved":false,"score":1,"score_hidden":false,"send_replies":true,"stickied":false,"subreddit":"macapps","subreddit_id":"t5_2rt9r","subreddit_name_prefixed":"r/macapps","subreddit_type":"public","top_awarded_type":null,"total_awards_received":0,"treatment_tags":[],"unrepliable_reason":null,"ups":1,"user_reports":[]},{"all_awardings":[],"approved_at_utc":null,"approved_by":null,"archived":false,"associated_award":null,"author":"mikepictor","author_flair_background_color":null,"author_flair_css_class":null,"author_flair_richtext":[],"author_flair_template_id":null,"author_flair_text":null,"author_flair_text_color":null,"author_flair_type":"text","author_fullname":"t2_68xr9","author_is_blocked":false,"author_patreon_flair":false,"author_premium":false,"awarders":[],"banned_at_utc":null,"banned_by":null,"body":"Such a good app. So worth the very very tiny license fee they charge.","body_html":"&lt;div class=\"md\"&gt;&lt;p&gt;Such a good app. So worth the very very tiny license fee they charge.&lt;/p&gt;\n&lt;/div&gt;","can_gild":false,"can_mod_post":false,"collapsed":false,"collapsed_because_crowd_control":null,"collapsed_reason":null,"collapsed_reason_code":null,"comment_type":null,"controversiality":0,"created":1727707791.0,"created_utc":1727707791.0,"distinguished":null,"downs":0,"edited":false,"gilded":0,"gildings":{},"id":"lpno085","is_submitter":false,"likes":null,"link_id":"t3_1fssvlt","locked":false,"mod_note":null,"mod_reason_by":null,"mod_reason_title":null,"mod_reports":[],"name":"t1_lpno085","no_follow":true,"num_reports":null,"parent_id":"t3_1fssvlt","permalink":"/r/macapps/comments/1fssvlt/shottr_18_released/lpno085/","removal_reason":null,"replies":"","report_reasons":null,"saved":false,"score":1,"score_hidden":false,"send_replies":true,"stickied":false,"subreddit":"macapps","subreddit_id":"t5_2rt9r","subreddit_name_prefixed":"r/macapps","subreddit_type":"public","top_awarded_type":null,"total_awards_received":0,"treatment_tags":[],"unrepliable_reason":null,"ups":1,"user_reports":[]},{"all_awardings":[],"approved_at_utc":null,"approved_by":null,"archived":false,"associated_award":null,"author":"ramysami4","author_flair_background_color":null,"author_flair_css_class":null,"author_flair_richtext":[],"author_flair_template_id":null,"author_flair_text":null,"author_flair_text_color":null,"author_flair_type":"text","author_fullname":"t2_105bmg","author_is_blocked":false,"author_patreon_flair":false,"author_premium":false,"awarders":[],"banned_at_utc":null,"banned_by":null,"body":"I wonder if the new version uses more ram","body_html":"&lt;div class=\"md\"&gt;&lt;p&gt;I wonder if the new version uses more ram&lt;/p&gt;\n&lt;/div&gt;","can_gild":false,"can_mod_post":false,"collapsed":false,"collapsed_because_crowd_control":null,"collapsed_reason":null,"collapsed_reason_code":null,"comment_type":null,"controversiality":0,"created":1727706542.0,"created_utc":1727706542.0,"distinguished":null,"downs":0,"edited":false,"gilded":0,"gildings":{},"id":"lpnkc9u","is_submitter":false,"likes":null,"link_id":"t3_1fssvlt","locked":false,"mod_note":null,"mod_reason_by":null,"mod_reason_title":null,"mod_reports":[],"name":"t1_lpnkc9u","no_follow":true,"num_reports":null,"parent_id":"t3_1fssvlt","permalink":"/r/macapps/comments/1fssvlt/shottr_18_released/lpnkc9u/","removal_reason":null,"replies":"","report_reasons":null,"saved":false,"score":1,"score_hidden":false,"send_replies":true,"stickied":false,"subreddit":"macapps","subreddit_id":"t5_2rt9r","subreddit_name_prefixed":"r/macapps","subreddit_type":"public","top_awarded_type":null,"total_awards_received":0,"treatment_tags":[],"unrepliable_reason":null,"ups":1,"user_reports":[]},{"all_awardings":[],"approved_at_utc":null,"approved_by":null,"archived":false,"associated_award":null,"author":"sherril8","author_flair_background_color":null,"author_flair_css_class":null,"author_flair_richtext":[],"author_flair_template_id":null,"author_flair_text":null,"author_flair_text_color":null,"author_flair_type":"text","author_fullname":"t2_3ouvl","author_is_blocked":false,"author_patreon_flair":false,"author_premium":false,"awarders":[],"banned_at_utc":null,"banned_by":null,"body":"In the email the dev sent out they said the prompt to update will roll out over several days but you can download it manually from the website.","body_html":"&lt;div class=\"md\"&gt;&lt;p&gt;In the email the dev sent out they said the prompt to update will roll out over several days but you can download it manually from the website.&lt;/p&gt;\n&lt;/div&gt;","can_gild":false,"can_mod_post":false,"collapsed":false,"collapsed_because_crowd_control":null,"collapsed_reason":null,"collapsed_reason_code":null,"comment_type":null,"controversiality":0,"created":1727706049.0,"created_utc":1727706049.0,"distinguished":null,"downs":0,"edited":false,"gilded":0,"gildings":{},"id":"lpnixlu","is_submitter":false,"likes":null,"link_id":"t3_1fssvlt","locked":false,"mod_note":null,"mod_reason_by":null,"mod_reason_title":null,"mod_reports":[],"name":"t1_lpnixlu","no_follow":true,"num_reports":null,"parent_id":"t1_lpmtaix","permalink":"/r/macapps/comments/1fssvlt/shottr_18_released/lpnixlu/","removal_reason":null,"replies":"","report_reasons":null,"saved":false,"score":1,"score_hidden":false,"send_replies":true,"stickied":false,"subreddit":"macapps","subreddit_id":"t5_2rt9r","subreddit_name_prefixed":"r/macapps","subreddit_type":"public","top_awarded_type":null,"total_awards_received":0,"treatment_tags":[],"unrepliable_reason":null,"ups":1,"user_reports":[]},{"all_awardings":[],"approved_at_utc":null,"approved_by":null,"archived":false,"associated_award":null,"author":"scottjl","author_flair_background_color":null,"author_flair_css_class":null,"author_flair_richtext":[],"author_flair_template_id":null,"author_flair_text":null,"author_flair_text_color":null,"author_flair_type":"text","author_fullname":"t2_urir","author_is_blocked":false,"author_patreon_flair":false,"author_premium":false,"awarders":[],"banned_at_utc":null,"banned_by":null,"body":"Thanks. I used to use that but it would hang on me a lot so I gave up. Maybe I\u2019ll give it another try.","body_html":"&lt;div class=\"md\"&gt;&lt;p&gt;Thanks. I used to use that but it would hang on me a lot so I gave up. Maybe I\u2019ll give it another try.&lt;/p&gt;\n&lt;/div&gt;","can_gild":false,"can_mod_post":false,"collapsed":false,"collapsed_because_crowd_control":null,"collapsed_reason":null,"collapsed_reason_code":null,"comment_type":null,"controversiality":0,"created":1727703738.0,"created_utc":1727703738.0,"distinguished":null,"downs":0,"edited":false,"gilded":0,"gildings":{},"id":"lpnckff","is_submitter":false,"likes":null,"link_id":"t3_1fssvlt","locked":false,"mod_note":null,"mod_reason_by":null,"mod_reason_title":null,"mod_reports":[],"name":"t1_lpnckff","no_follow":true,"num_reports":null,"parent_id":"t1_lpnbyib","permalink":"/r/macapps/comments/1fssvlt/shottr_18_released/lpnckff/","removal_reason":null,"replies":"","report_reasons":null,"saved":false,"score":1,"score_hidden":false,"send_replies":true,"stickied":false,"subreddit":"macapps","subreddit_id":"t5_2rt9r","subreddit_name_prefixed":"r/macapps","subreddit_type":"public","top_awarded_type":null,"total_awards_received":0,"treatment_tags":[],"unrepliable_reason":null,"ups":1,"user_reports":[]},{"all_awardings":[],"approved_at_utc":null,"approved_by":null,"archived":false,"associated_award":null,"author":"QenTox","author_flair_background_color":null,"author_flair_css_class":null,"author_flair_richtext":[],"author_flair_template_id":null,"author_flair_text":null,"author_flair_text_color":null,"author_flair_type":"text","author_fullname":"t2_14t694","author_is_blocked":false,"author_patreon_flair":false,"author_premium":false,"awarders":[],"banned_at_utc":null,"banned_by":null,"body":"I use the [Latest](https://max.codes/latest/) app daily,\u00a0so I learned about the update there,\u00a0but I was still trying to figure out how to update Shottr.","body_html":"&lt;div class=\"md\"&gt;&lt;p&gt;I use the &lt;a href=\"https://max.codes/latest/\"&gt;Latest&lt;/a&gt; app daily,\u00a0so I learned about the update there,\u00a0but I was still trying to figure out how to update Shottr.&lt;/p&gt;\n&lt;/div&gt;","can_gild":false,"can_mod_post":false,"collapsed":false,"collapsed_because_crowd_control":null,"collapsed_reason":null,"collapsed_reason_code":null,"comment_type":null,"controversiality":0,"created":1727703507.0,"created_utc":1727703507.0,"distinguished":null,"downs":0,"edited":false,"gilded":0,"gildings":{},"id":"lpnbyib","is_submitter":false,"likes":null,"link_id":"t3_1fssvlt","locked":false,"mod_note":null,"mod_reason_by":null,"mod_reason_title":null,"mod_reports":[],"name":"t1_lpnbyib","no_follow":true,"num_reports":null,"parent_id":"t1_lpnb2kh","permalink":"/r/macapps/comments/1fssvlt/shottr_18_released/lpnbyib/","removal_reason":null,"replies":"","report_reasons":null,"saved":false,"score":1,"score_hidden":false,"send_replies":true,"stickied":false,"subreddit":"macapps","subreddit_id":"t5_2rt9r","subreddit_name_prefixed":"r/macapps","subreddit_type":"public","top_awarded_type":null,"total_awards_received":0,"treatment_tags":[],"unrepliable_reason":null,"ups":1,"user_reports":[]},{"all_awardings":[],"approved_at_utc":null,"approved_by":null,"archived":false,"associated_award":null,"author":"nezia","author_flair_background_color":null,"author_flair_css_class":null,"author_flair_richtext":[],"author_flair_template_id":null,"author_flair_text":null,"author_flair_text_color":null,"author_flair_type":"text","author_fullname":"t2_e2kla","author_is_blocked":false,"author_patreon_flair":false,"author_premium":false,"awarders":[],"banned_at_utc":null,"banned_by":null,"body":"Is there now a way to clear the old screenshot from the editor window after some time has passed?","body_html":"&lt;div class=\"md\"&gt;&lt;p&gt;Is there now a way to clear the old screenshot from the editor window after some time has passed?&lt;/p&gt;\n&lt;/div&gt;","can_gild":false,"can_mod_post":false,"collapsed":false,"collapsed_because_crowd_control":null,"collapsed_reason":null,"collapsed_reason_code":null,"comment_type":null,"controversiality":0,"created":1727703364.0,"created_utc":1727703364.0,"distinguished":null,"downs":0,"edited":false,"gilded":0,"gildings":{},"id":"lpnblzk","is_submitter":false,"likes":null,"link_id":"t3_1fssvlt","locked":false,"mod_note":null,"mod_reason_by":null,"mod_reason_title":null,"mod_reports":[],"name":"t1_lpnblzk","no_follow":true,"num_reports":null,"parent_id":"t3_1fssvlt","permalink":"/r/macapps/comments/1fssvlt/shottr_18_released/lpnblzk/","removal_reason":null,"replies":"","report_reasons":null,"saved":false,"score":1,"score_hidden":false,"send_replies":true,"stickied":false,"subreddit":"macapps","subreddit_id":"t5_2rt9r","subreddit_name_prefixed":"r/macapps","subreddit_type":"public","top_awarded_type":null,"total_awards_received":0,"treatment_tags":[],"unrepliable_reason":null,"ups":1,"user_reports":[]},{"all_awardings":[],"approved_at_utc":null,"approved_by":null,"archived":false,"associated_award":null,"author":"scottjl","author_flair_background_color":null,"author_flair_css_class":null,"author_flair_richtext":[],"author_flair_template_id":null,"author_flair_text":null,"author_flair_text_color":null,"author_flair_type":"text","author_fullname":"t2_urir","author_is_blocked":false,"author_patreon_flair":false,"author_premium":false,"awarders":[],"banned_at_utc":null,"banned_by":null,"body":"i agree. at least notify me there's a new version available. if i didn't happen to stumble on this post i wouldn't have known!","body_html":"&lt;div class=\"md\"&gt;&lt;p&gt;i agree. at least notify me there&amp;#39;s a new version available. if i didn&amp;#39;t happen to stumble on this post i wouldn&amp;#39;t have known!&lt;/p&gt;\n&lt;/div&gt;","can_gild":false,"can_mod_post":false,"collapsed":false,"collapsed_because_crowd_control":null,"collapsed_reason":null,"collapsed_reason_code":null,"comment_type":null,"controversiality":0,"created":1727703147.0,"created_utc":1727703147.0,"distinguished":null,"downs":0,"edited":false,"gilded":0,"gildings":{},"id":"lpnb2kh","is_submitter":false,"likes":null,"link_id":"t3_1fssvlt","locked":false,"mod_note":null,"mod_reason_by":null,"mod_reason_title":null,"mod_reports":[],"name":"t1_lpnb2kh","no_follow":true,"num_reports":null,"parent_id":"t1_lpmtosh","permalink":"/r/macapps/comments/1fssvlt/shottr_18_released/lpnb2kh/","removal_reason":null,"replies":"","report_reasons":null,"saved":false,"score":1,"score_hidden":false,"send_replies":true,"stickied":false,"subreddit":"macapps","subreddit_id":"t5_2rt9r","subreddit_name_prefixed":"r/macapps","subreddit_type":"public","top_awarded_type":null,"total_awards_received":0,"treatment_tags":[],"unrepliable_reason":null,"ups":1,"user_reports":[]},{"all_awardings":[],"approved_at_utc":null,"approved_by":null,"archived":false,"associated_award":null,"author":"nez329","author_flair_background_color":null,"author_flair_css_class":null,"author_flair_richtext":[],"author_flair_template_id":null,"author_flair_text":null,"author_flair_text_color":null,"author_flair_type":"text","author_fullname":"t2_438u6s0j","author_is_blocked":false,"author_patreon_flair":false,"author_premium":false,"awarders":[],"banned_at_utc":null,"banned_by":null,"body":"It was. \n\nOne of the universe mysteries.","body_html":"&lt;div class=\"md\"&gt;&lt;p&gt;It was. &lt;/p&gt;\n\n&lt;p&gt;One of the universe mysteries.&lt;/p&gt;\n&lt;/div&gt;","can_gild":false,"can_mod_post":false,"collapsed":false,"collapsed_because_crowd_control":null,"collapsed_reason":null,"collapsed_reason_code":null,"comment_type":null,"controversiality":0,"created":1727702927.0,"created_utc":1727702927.0,"distinguished":null,"downs":0,"edited":false,"gilded":0,"gildings":{},"id":"lpnaiih","is_submitter":false,"likes":null,"link_id":"t3_1fssvlt","locked":false,"mod_note":null,"mod_reason_by":null,"mod_reason_title":null,"mod_reports":[],"name":"t1_lpnaiih","no_follow":true,"num_reports":null,"parent_id":"t1_lpna30j","permalink":"/r/macapps/comments/1fssvlt/shottr_18_released/lpnaiih/","removal_reason":null,"replies":"","report_reasons":null,"saved":false,"score":1,"score_hidden":false,"send_replies":true,"stickied":false,"subreddit":"macapps","subreddit_id":"t5_2rt9r","subreddit_name_prefixed":"r/macapps","subreddit_type":"public","top_awarded_type":null,"total_awards_received":0,"treatment_tags":[],"unrepliable_reason":null,"ups":1,"user_reports":[]},{"all_awardings":[],"approved_at_utc":null,"approved_by":null,"archived":false,"associated_award":null,"author":"No-Caregiver8049","author_flair_background_color":null,"author_flair_css_class":null,"author_flair_richtext":[],"author_flair_template_id":null,"author_flair_text":null,"author_flair_text_color":null,"author_flair_type":"text","author_fullname":"t2_w2yjo5zg","author_is_blocked":false,"author_patreon_flair":false,"author_premium":false,"awarders":[],"banned_at_utc":null,"banned_by":null,"body":"Sorry your gasts were flabbered.  Must have been awful.","body_html":"&lt;div class=\"md\"&gt;&lt;p&gt;Sorry your gasts were flabbered.  Must have been awful.&lt;/p&gt;\n&lt;/div&gt;","can_gild":false,"can_mod_post":false,"collapsed":false,"collapsed_because_crowd_control":null,"collapsed_reason":null,"collapsed_reason_code":null,"comment_type":null,"controversiality":0,"created":1727702759.0,"created_utc":1727702759.0,"distinguished":null,"downs":0,"edited":false,"gilded":0,"gildings":{},"id":"lpna30j","is_submitter":false,"likes":null,"link_id":"t3_1fssvlt","locked":false,"mod_note":null,"mod_reason_by":null,"mod_reason_title":null,"mod_reports":[],"name":"t1_lpna30j","no_follow":true,"num_reports":null,"parent_id":"t1_lpn9amd","permalink":"/r/macapps/comments/1fssvlt/shottr_18_released/lpna30j/","removal_reason":null,"replies":"","report_reasons":null,"saved":false,"score":1,"score_hidden":false,"send_replies":true,"stickied":false,"subreddit":"macapps","subreddit_id":"t5_2rt9r","subreddit_name_prefixed":"r/macapps","subreddit_type":"public","top_awarded_type":null,"total_awards_received":0,"treatment_tags":[],"unrepliable_reason":null,"ups":1,"user_reports":[]},{"all_awardings":[],"approved_at_utc":null,"approved_by":null,"archived":false,"associated_award":null,"author":"nez329","author_flair_background_color":null,"author_flair_css_class":null,"author_flair_richtext":[],"author_flair_template_id":null,"author_flair_text":null,"author_flair_text_color":null,"author_flair_type":"text","author_fullname":"t2_438u6s0j","author_is_blocked":false,"author_patreon_flair":false,"author_premium":false,"awarders":[],"banned_at_utc":null,"banned_by":null,"body":"Cause I needed to. One day I did a screenshot with Shottr then need to rotate the image, looked high, look low and could not find it. \n\nAsked in Reddit and was told Shottr do not have Rotate. \n\nI was flabbergasted.","body_html":"&lt;div class=\"md\"&gt;&lt;p&gt;Cause I needed to. One day I did a screenshot with Shottr then need to rotate the image, looked high, look low and could not find it. &lt;/p&gt;\n\n&lt;p&gt;Asked in Reddit and was told Shottr do not have Rotate. &lt;/p&gt;\n\n&lt;p&gt;I was flabbergasted.&lt;/p&gt;\n&lt;/div&gt;","can_gild":false,"can_mod_post":false,"collapsed":false,"collapsed_because_crowd_control":null,"collapsed_reason":null,"collapsed_reason_code":null,"comment_type":null,"controversiality":0,"created":1727702446.0,"created_utc":1727702446.0,"distinguished":null,"downs":0,"edited":false,"gilded":0,"gildings":{},"id":"lpn9amd","is_submitter":false,"likes":null,"link_id":"t3_1fssvlt","locked":false,"mod_note":null,"mod_reason_by":null,"mod_reason_title":null,"mod_reports":[],"name":"t1_lpn9amd","no_follow":true,"num_reports":null,"parent_id":"t1_lpn8kbn","permalink":"/r/macapps/comments/1fssvlt/shottr_18_released/lpn9amd/","removal_reason":null,"replies":"","report_reasons":null,"saved":false,"score":1,"score_hidden":false,"send_replies":true,"stickied":false,"subreddit":"macapps","subreddit_id":"t5_2rt9r","subreddit_name_prefixed":"r/macapps","subreddit_type":"public","top_awarded_type":null,"total_awards_received":0,"treatment_tags":[],"unrepliable_reason":null,"ups":1,"user_reports":[]},{"all_awardings":[],"approved_at_utc":null,"approved_by":null,"archived":false,"associated_award":null,"author":"amerpie","author_flair_background_color":null,"author_flair_css_class":null,"author_flair_richtext":[],"author_flair_template_id":null,"author_flair_text":null,"author_flair_text_color":null,"author_flair_type":"text","author_fullname":"t2_2xbm","author_is_blocked":false,"author_patreon_flair":false,"author_premium":true,"awarders":[],"banned_at_utc":null,"banned_by":null,"body":"Not the dev but curious as to why you want to rotate a screenshot.","body_html":"&lt;div class=\"md\"&gt;&lt;p&gt;Not the dev but curious as to why you want to rotate a screenshot.&lt;/p&gt;\n&lt;/div&gt;","can_gild":false,"can_mod_post":false,"collapsed":false,"collapsed_because_crowd_control":null,"collapsed_reason":null,"collapsed_reason_code":null,"comment_type":null,"controversiality":0,"created":1727702159.0,"created_utc":1727702159.0,"distinguished":null,"downs":0,"edited":false,"gilded":0,"gildings":{},"id":"lpn8kbn","is_submitter":true,"likes":null,"link_id":"t3_1fssvlt","locked":false,"mod_note":null,"mod_reason_by":null,"mod_reason_title":null,"mod_reports":[],"name":"t1_lpn8kbn","no_follow":true,"num_reports":null,"parent_id":"t1_lpn7z22","permalink":"/r/macapps/comments/1fssvlt/shottr_18_released/lpn8kbn/","removal_reason":null,"replies":"","report_reasons":null,"saved":false,"score":1,"score_hidden":false,"send_replies":true,"stickied":false,"subreddit":"macapps","subreddit_id":"t5_2rt9r","subreddit_name_prefixed":"r/macapps","subreddit_type":"public","top_awarded_type":null,"total_awards_received":0,"treatment_tags":[],"unrepliable_reason":null,"ups":1,"user_reports":[]},{"all_awardings":[],"approved_at_utc":null,"approved_by":null,"archived":false,"associated_award":null,"author":"Adventurous-Row-2291","author_flair_background_color":null,"author_flair_css_class":null,"author_flair_richtext":[],"author_flair_template_id":null,"author_flair_text":null,"author_flair_text_color":null,"author_flair_type":"text","author_fullname":"t2_7xqtppes","author_is_blocked":false,"author_patreon_flair":false,"author_premium":false,"awarders":[],"banned_at_utc":null,"banned_by":null,"body":"Great App - looking forward to updating - thank you","body_html":"&lt;div class=\"md\"&gt;&lt;p&gt;Great App - looking forward to updating - thank you&lt;/p&gt;\n&lt;/div&gt;","can_gild":false,"can_mod_post":false,"collapsed":false,"collapsed_because_crowd_control":null,"collapsed_reason":null,"collapsed_reason_code":null,"comment_type":null,"controversiality":0,"created":1727702060.0,"created_utc":1727702060.0,"distinguished":null,"downs":0,"edited":false,"gilded":0,"gildings":{},"id":"lpn8bdh","is_submitter":false,"likes":null,"link_id":"t3_1fssvlt","locked":false,"mod_note":null,"mod_reason_by":null,"mod_reason_title":null,"mod_reports":[],"name":"t1_lpn8bdh","no_follow":true,"num_reports":null,"parent_id":"t3_1fssvlt","permalink":"/r/macapps/comments/1fssvlt/shottr_18_released/lpn8bdh/","removal_reason":null,"replies":"","report_reasons":null,"saved":false,"score":1,"score_hidden":false,"send_replies":true,"stickied":false,"subreddit":"macapps","subreddit_id":"t5_2rt9r","subreddit_name_prefixed":"r/macapps","subreddit_type":"public","top_awarded_type":null,"total_awards_received":0,"treatment_tags":[],"unrepliable_reason":null,"ups":1,"user_reports":[]},{"all_awardings":[],"approved_at_utc":null,"approved_by":null,"archived":false,"associated_award":null,"author":"nez329","author_flair_background_color":null,"author_flair_css_class":null,"author_flair_richtext":[],"author_flair_template_id":null,"author_flair_text":null,"author_flair_text_color":null,"author_flair_type":"text","author_fullname":"t2_438u6s0j","author_is_blocked":false,"author_patreon_flair":false,"author_premium":false,"awarders":[],"banned_at_utc":null,"banned_by":null,"body":"No Rotate function?\n\nSeriously?","body_html":"&lt;div class=\"md\"&gt;&lt;p&gt;No Rotate function?&lt;/p&gt;\n\n&lt;p&gt;Seriously?&lt;/p&gt;\n&lt;/div&gt;","can_gild":false,"can_mod_post":false,"collapsed":false,"collapsed_because_crowd_control":null,"collapsed_reason":null,"collapsed_reason_code":null,"comment_type":null,"controversiality":0,"created":1727701923.0,"created_utc":1727701923.0,"distinguished":null,"downs":0,"edited":false,"gilded":0,"gildings":{},"id":"lpn7z22","is_submitter":false,"likes":null,"link_id":"t3_1fssvlt","locked":false,"mod_note":null,"mod_reason_by":null,"mod_reason_title":null,"mod_reports":[],"name":"t1_lpn7z22","no_follow":true,"num_reports":null,"parent_id":"t3_1fssvlt","permalink":"/r/macapps/comments/1fssvlt/shottr_18_released/lpn7z22/","removal_reason":null,"replies":"","report_reasons":null,"saved":false,"score":1,"score_hidden":false,"send_replies":true,"stickied":false,"subreddit":"macapps","subreddit_id":"t5_2rt9r","subreddit_name_prefixed":"r/macapps","subreddit_type":"public","top_awarded_type":null,"total_awards_received":0,"treatment_tags":[],"unrepliable_reason":null,"ups":1,"user_reports":[]},{"_meta":{"is_edited":true,"retrieved_2nd_on":1727831533},"all_awardings":[],"approved_at_utc":null,"approved_by":null,"archived":false,"associated_award":null,"author":"nez329","author_flair_background_color":null,"author_flair_css_class":null,"author_flair_richtext":[],"author_flair_template_id":null,"author_flair_text":null,"author_flair_text_color":null,"author_flair_type":"text","author_fullname":"t2_438u6s0j","author_is_blocked":false,"author_patreon_flair":false,"author_premium":false,"awarders":[],"banned_at_utc":null,"banned_by":null,"body":"No Rotate function?","can_gild":false,"can_mod_post":false,"collapsed":false,"collapsed_because_crowd_control":null,"collapsed_reason":null,"collapsed_reason_code":null,"comment_type":null,"controversiality":0,"created":1727701923.0,"created_utc":1727701923.0,"distinguished":null,"downs":0,"edited":false,"gilded":0,"gildings":{},"id":"lpn7z22","is_submitter":false,"likes":null,"link_id":"t3_1fssvlt","locked":false,"mod_note":null,"mod_reason_by":null,"mod_reason_title":null,"mod_reports":[],"name":"t1_lpn7z22","no_follow":true,"num_reports":0,"parent_id":"t3_1fssvlt","permalink":"/r/macapps/comments/1fssvlt/shottr_18_released/lpn7z22/","removal_reason":null,"replies":"","report_reasons":[],"retrieved_on":1727701940,"saved":false,"score":-4,"score_hidden":false,"send_replies":true,"stickied":false,"subreddit":"macapps","subreddit_id":"t5_2rt9r","subreddit_name_prefixed":"r/macapps","subreddit_type":"public","top_awarded_type":null,"total_awards_received":0,"treatment_tags":[],"unrepliable_reason":null,"updated_on":1727701954,"ups":-4,"user_reports":[]},{"all_awardings":[],"approved_at_utc":null,"approved_by":null,"archived":false,"associated_award":null,"author":"gsbansal10","author_flair_background_color":null,"author_flair_css_class":null,"author_flair_richtext":[],"author_flair_template_id":null,"author_flair_text":null,"author_flair_text_color":null,"author_flair_type":"text","author_fullname":"t2_71fvhqh0","author_is_blocked":false,"author_patreon_flair":false,"author_premium":false,"awarders":[],"banned_at_utc":null,"banned_by":null,"body":"There's a setting to do just that. I have it enabled. Its something like \"after taking screenshot:\" copy to clipboard or ooen editor....","body_html":"&lt;div class=\"md\"&gt;&lt;p&gt;There&amp;#39;s a setting to do just that. I have it enabled. Its something like &amp;quot;after taking screenshot:&amp;quot; copy to clipboard or ooen editor....&lt;/p&gt;\n&lt;/div&gt;","can_gild":false,"can_mod_post":false,"collapsed":false,"collapsed_because_crowd_control":null,"collapsed_reason":null,"collapsed_reason_code":null,"comment_type":null,"controversiality":0,"created":1727701064.0,"created_utc":1727701064.0,"distinguished":null,"downs":0,"edited":false,"gilded":0,"gildings":{},"id":"lpn5vgp","is_submitter":false,"likes":null,"link_id":"t3_1fssvlt","locked":false,"mod_note":null,"mod_reason_by":null,"mod_reason_title":null,"mod_reports":[],"name":"t1_lpn5vgp","no_follow":true,"num_reports":null,"parent_id":"t1_lpmxqxd","permalink":"/r/macapps/comments/1fssvlt/shottr_18_released/lpn5vgp/","removal_reason":null,"replies":"","report_reasons":null,"saved":false,"score":1,"score_hidden":false,"send_replies":true,"stickied":false,"subreddit":"macapps","subreddit_id":"t5_2rt9r","subreddit_name_prefixed":"r/macapps","subreddit_type":"public","top_awarded_type":null,"total_awards_received":0,"treatment_tags":[],"unrepliable_reason":null,"ups":1,"user_reports":[]},{"all_awardings":[],"approved_at_utc":null,"approved_by":null,"archived":false,"associated_award":null,"author":"givebest","author_flair_background_color":null,"author_flair_css_class":null,"author_flair_richtext":[],"author_flair_template_id":null,"author_flair_text":null,"author_flair_text_color":null,"author_flair_type":"text","author_fullname":"t2_lx3vojk","author_is_blocked":false,"author_patreon_flair":false,"author_premium":false,"awarders":[],"banned_at_utc":null,"banned_by":null,"body":"I've been using it for a while now, and with the new features, it's getting better and better!","body_html":"&lt;div class=\"md\"&gt;&lt;p&gt;I&amp;#39;ve been using it for a while now, and with the new features, it&amp;#39;s getting better and better!&lt;/p&gt;\n&lt;/div&gt;","can_gild":false,"can_mod_post":false,"collapsed":false,"collapsed_because_crowd_control":null,"collapsed_reason":null,"collapsed_reason_code":null,"comment_type":null,"controversiality":0,"created":1727699936.0,"created_utc":1727699936.0,"distinguished":null,"downs":0,"edited":false,"gilded":0,"gildings":{},"id":"lpn37lk","is_submitter":false,"likes":null,"link_id":"t3_1fssvlt","locked":false,"mod_note":null,"mod_reason_by":null,"mod_reason_title":null,"mod_reports":[],"name":"t1_lpn37lk","no_follow":true,"num_reports":null,"parent_id":"t3_1fssvlt","permalink":"/r/macapps/comments/1fssvlt/shottr_18_released/lpn37lk/","removal_reason":null,"replies":"","report_reasons":null,"saved":false,"score":1,"score_hidden":false,"send_replies":true,"stickied":false,"subreddit":"macapps","subreddit_id":"t5_2rt9r","subreddit_name_prefixed":"r/macapps","subreddit_type":"public","top_awarded_type":null,"total_awards_received":0,"treatment_tags":[],"unrepliable_reason":null,"ups":1,"user_reports":[]},{"all_awardings":[],"approved_at_utc":null,"approved_by":null,"archived":false,"associated_award":null,"author":"amerpie","author_flair_background_color":null,"author_flair_css_class":null,"author_flair_richtext":[],"author_flair_template_id":null,"author_flair_text":null,"author_flair_text_color":null,"author_flair_type":"text","author_fullname":"t2_2xbm","author_is_blocked":false,"author_patreon_flair":false,"author_premium":true,"awarders":[],"banned_at_utc":null,"banned_by":null,"body":"I'm not the dev. You'll need to reach out to him through the web site.","body_html":"&lt;div class=\"md\"&gt;&lt;p&gt;I&amp;#39;m not the dev. You&amp;#39;ll need to reach out to him through the web site.&lt;/p&gt;\n&lt;/div&gt;","can_gild":false,"can_mod_post":false,"collapsed":false,"collapsed_because_crowd_control":null,"collapsed_reason":null,"collapsed_reason_code":null,"comment_type":null,"controversiality":0,"created":1727697655.0,"created_utc":1727697655.0,"distinguished":null,"downs":0,"edited":false,"gilded":0,"gildings":{},"id":"lpmy9i8","is_submitter":true,"likes":null,"link_id":"t3_1fssvlt","locked":false,"mod_note":null,"mod_reason_by":null,"mod_reason_title":null,"mod_reports":[],"name":"t1_lpmy9i8","no_follow":true,"num_reports":null,"parent_id":"t1_lpmxufi","permalink":"/r/macapps/comments/1fssvlt/shottr_18_released/lpmy9i8/","removal_reason":null,"replies":"","report_reasons":null,"saved":false,"score":1,"score_hidden":false,"send_replies":true,"stickied":false,"subreddit":"macapps","subreddit_id":"t5_2rt9r","subreddit_name_prefixed":"r/macapps","subreddit_type":"public","top_awarded_type":null,"total_awards_received":0,"treatment_tags":[],"unrepliable_reason":null,"ups":1,"user_reports":[]},{"all_awardings":[],"approved_at_utc":null,"approved_by":null,"archived":false,"associated_award":null,"author":"Ariochar","author_flair_background_color":null,"author_flair_css_class":null,"author_flair_richtext":[],"author_flair_template_id":null,"author_flair_text":null,"author_flair_text_color":null,"author_flair_type":"text","author_fullname":"t2_18kv5k61","author_is_blocked":false,"author_patreon_flair":false,"author_premium":false,"awarders":[],"banned_at_utc":null,"banned_by":null,"body":"Seems really nice! I\u2019ll give it a try. \nQuick question, what did you used to do the presentation video on your website?","body_html":"&lt;div class=\"md\"&gt;&lt;p&gt;Seems really nice! I\u2019ll give it a try. \nQuick question, what did you used to do the presentation video on your website?&lt;/p&gt;\n&lt;/div&gt;","can_gild":false,"can_mod_post":false,"collapsed":false,"collapsed_because_crowd_control":null,"collapsed_reason":null,"collapsed_reason_code":null,"comment_type":null,"controversiality":0,"created":1727697454.0,"created_utc":1727697454.0,"distinguished":null,"downs":0,"edited":false,"gilded":0,"gildings":{},"id":"lpmxufi","is_submitter":false,"likes":null,"link_id":"t3_1fssvlt","locked":false,"mod_note":null,"mod_reason_by":null,"mod_reason_title":null,"mod_reports":[],"name":"t1_lpmxufi","no_follow":false,"num_reports":null,"parent_id":"t3_1fssvlt","permalink":"/r/macapps/comments/1fssvlt/shottr_18_released/lpmxufi/","removal_reason":null,"replies":"","report_reasons":null,"saved":false,"score":1,"score_hidden":false,"send_replies":true,"stickied":false,"subreddit":"macapps","subreddit_id":"t5_2rt9r","subreddit_name_prefixed":"r/macapps","subreddit_type":"public","top_awarded_type":null,"total_awards_received":0,"treatment_tags":[],"unrepliable_reason":null,"ups":1,"user_reports":[]},{"all_awardings":[],"approved_at_utc":null,"approved_by":null,"archived":false,"associated_award":null,"author":"[deleted]","author_flair_background_color":"","author_flair_css_class":null,"author_flair_template_id":null,"author_flair_text":null,"author_flair_text_color":"dark","author_is_blocked":false,"awarders":[],"banned_at_utc":null,"banned_by":null,"body":"[deleted]","body_html":"&lt;div class=\"md\"&gt;&lt;p&gt;[deleted]&lt;/p&gt;\n&lt;/div&gt;","can_gild":false,"can_mod_post":false,"collapsed":true,"collapsed_because_crowd_control":null,"collapsed_reason":null,"collapsed_reason_code":"DELETED","comment_type":null,"controversiality":0,"created":1727697407.0,"created_utc":1727697407.0,"distinguished":null,"downs":0,"edited":false,"gilded":0,"gildings":{},"id":"lpmxqxd","is_submitter":false,"likes":null,"link_id":"t3_1fssvlt","locked":false,"mod_note":null,"mod_reason_by":null,"mod_reason_title":null,"mod_reports":[],"name":"t1_lpmxqxd","no_follow":true,"num_reports":null,"parent_id":"t3_1fssvlt","permalink":"/r/macapps/comments/1fssvlt/shottr_18_released/lpmxqxd/","removal_reason":null,"replies":"","report_reasons":null,"saved":false,"score":1,"score_hidden":false,"send_replies":true,"stickied":false,"subreddit":"macapps","subreddit_id":"t5_2rt9r","subreddit_name_prefixed":"r/macapps","subreddit_type":"public","top_awarded_type":null,"total_awards_received":0,"treatment_tags":[],"unrepliable_reason":null,"ups":1,"user_reports":[]},{"all_awardings":[],"approved_at_utc":null,"approved_by":null,"archived":false,"associated_award":null,"author":"Tralalouti","author_flair_background_color":null,"author_flair_css_class":null,"author_flair_richtext":[],"author_flair_template_id":null,"author_flair_text":null,"author_flair_text_color":null,"author_flair_type":"text","author_fullname":"t2_d1xtref9","author_is_blocked":false,"author_patreon_flair":false,"author_premium":false,"awarders":[],"banned_at_utc":null,"banned_by":null,"body":"Love the app so far, thank you :)\n\nWas wondering how to set up different shortcuts to :\n\n- take a screenshot + copy clipboard without opening the editor\n\n- take a screenshot + open the editor\n\nThank you.","body_html":"&lt;div class=\"md\"&gt;&lt;p&gt;Love the app so far, thank you :)&lt;/p&gt;\n\n&lt;p&gt;Was wondering how to set up different shortcuts to :&lt;/p&gt;\n\n&lt;ul&gt;\n&lt;li&gt;&lt;p&gt;take a screenshot + copy clipboard without opening the editor&lt;/p&gt;&lt;/li&gt;\n&lt;li&gt;&lt;p&gt;take a screenshot + open the editor&lt;/p&gt;&lt;/li&gt;\n&lt;/ul&gt;\n\n&lt;p&gt;Thank you.&lt;/p&gt;\n&lt;/div&gt;","can_gild":false,"can_mod_post":false,"collapsed":false,"collapsed_because_crowd_control":null,"collapsed_reason":null,"collapsed_reason_code":null,"comment_type":null,"controversiality":0,"created":1727697407.0,"created_utc":1727697407.0,"distinguished":null,"downs":0,"edited":false,"gilded":0,"gildings":{},"id":"lpmxqxd","is_submitter":false,"likes":null,"link_id":"t3_1fssvlt","locked":false,"mod_note":null,"mod_reason_by":null,"mod_reason_title":null,"mod_reports":[],"name":"t1_lpmxqxd","no_follow":true,"num_reports":null,"parent_id":"t3_1fssvlt","permalink":"/r/macapps/comments/1fssvlt/shottr_18_released/lpmxqxd/","removal_reason":null,"replies":"","report_reasons":null,"saved":false,"score":1,"score_hidden":false,"send_replies":true,"stickied":false,"subreddit":"macapps","subreddit_id":"t5_2rt9r","subreddit_name_prefixed":"r/macapps","subreddit_type":"public","top_awarded_type":null,"total_awards_received":0,"treatment_tags":[],"unrepliable_reason":null,"ups":1,"user_reports":[]},{"all_awardings":[],"approved_at_utc":null,"approved_by":null,"archived":false,"associated_award":null,"author":"QenTox","author_flair_background_color":null,"author_flair_css_class":null,"author_flair_richtext":[],"author_flair_template_id":null,"author_flair_text":null,"author_flair_text_color":null,"author_flair_type":"text","author_fullname":"t2_14t694","author_is_blocked":false,"author_patreon_flair":false,"author_premium":false,"awarders":[],"banned_at_utc":null,"banned_by":null,"body":"There was no update for a long time, so I forgot what way Shottr needs to be updated, thanks for confirming!\n\nSuch a popular app could really implement some sort of auto-update IMO.","body_html":"&lt;div class=\"md\"&gt;&lt;p&gt;There was no update for a long time, so I forgot what way Shottr needs to be updated, thanks for confirming!&lt;/p&gt;\n\n&lt;p&gt;Such a popular app could really implement some sort of auto-update IMO.&lt;/p&gt;\n&lt;/div&gt;","can_gild":false,"can_mod_post":false,"collapsed":false,"collapsed_because_crowd_control":null,"collapsed_reason":null,"collapsed_reason_code":null,"comment_type":null,"controversiality":0,"created":1727695346.0,"created_utc":1727695346.0,"distinguished":null,"downs":0,"edited":false,"gilded":0,"gildings":{},"id":"lpmtosh","is_submitter":false,"likes":null,"link_id":"t3_1fssvlt","locked":false,"mod_note":null,"mod_reason_by":null,"mod_reason_title":null,"mod_reports":[],"name":"t1_lpmtosh","no_follow":true,"num_reports":null,"parent_id":"t1_lpmtekl","permalink":"/r/macapps/comments/1fssvlt/shottr_18_released/lpmtosh/","removal_reason":null,"replies":"","report_reasons":null,"saved":false,"score":1,"score_hidden":false,"send_replies":true,"stickied":false,"subreddit":"macapps","subreddit_id":"t5_2rt9r","subreddit_name_prefixed":"r/macapps","subreddit_type":"public","top_awarded_type":null,"total_awards_received":0,"treatment_tags":[],"unrepliable_reason":null,"ups":1,"user_reports":[]},{"all_awardings":[],"approved_at_utc":null,"approved_by":null,"archived":false,"associated_award":null,"author":"amerpie","author_flair_background_color":null,"author_flair_css_class":null,"author_flair_richtext":[],"author_flair_template_id":null,"author_flair_text":null,"author_flair_text_color":null,"author_flair_type":"text","author_fullname":"t2_2xbm","author_is_blocked":false,"author_patreon_flair":false,"author_premium":true,"awarders":[],"banned_at_utc":null,"banned_by":null,"body":"I just went to the website and downloaded the new version. https://shottr.cc/","body_html":"&lt;div class=\"md\"&gt;&lt;p&gt;I just went to the website and downloaded the new version. &lt;a href=\"https://shottr.cc/\"&gt;https://shottr.cc/&lt;/a&gt;&lt;/p&gt;\n&lt;/div&gt;","can_gild":false,"can_mod_post":false,"collapsed":false,"collapsed_because_crowd_control":null,"collapsed_reason":null,"collapsed_reason_code":null,"comment_type":null,"controversiality":0,"created":1727695195.0,"created_utc":1727695195.0,"distinguished":null,"downs":0,"edited":false,"gilded":0,"gildings":{},"id":"lpmtekl","is_submitter":true,"likes":null,"link_id":"t3_1fssvlt","locked":false,"mod_note":null,"mod_reason_by":null,"mod_reason_title":null,"mod_reports":[],"name":"t1_lpmtekl","no_follow":true,"num_reports":null,"parent_id":"t1_lpmtaix","permalink":"/r/macapps/comments/1fssvlt/shottr_18_released/lpmtekl/","removal_reason":null,"replies":"","report_reasons":null,"saved":false,"score":1,"score_hidden":false,"send_replies":true,"stickied":false,"subreddit":"macapps","subreddit_id":"t5_2rt9r","subreddit_name_prefixed":"r/macapps","subreddit_type":"public","top_awarded_type":null,"total_awards_received":0,"treatment_tags":[],"unrepliable_reason":null,"ups":1,"user_reports":[]},{"all_awardings":[],"approved_at_utc":null,"approved_by":null,"archived":false,"associated_award":null,"author":"QenTox","author_flair_background_color":null,"author_flair_css_class":null,"author_flair_richtext":[],"author_flair_template_id":null,"author_flair_text":null,"author_flair_text_color":null,"author_flair_type":"text","author_fullname":"t2_14t694","author_is_blocked":false,"author_patreon_flair":false,"author_premium":false,"awarders":[],"banned_at_utc":null,"banned_by":null,"body":"How do you update it? Only manually or am I missing the obvious option somewhere hidden?","body_html":"&lt;div class=\"md\"&gt;&lt;p&gt;How do you update it? Only manually or am I missing the obvious option somewhere hidden?&lt;/p&gt;\n&lt;/div&gt;","can_gild":false,"can_mod_post":false,"collapsed":false,"collapsed_because_crowd_control":null,"collapsed_reason":null,"collapsed_reason_code":null,"comment_type":null,"controversiality":0,"created":1727695134.0,"created_utc":1727695134.0,"distinguished":null,"downs":0,"edited":false,"gilded":0,"gildings":{},"id":"lpmtaix","is_submitter":false,"likes":null,"link_id":"t3_1fssvlt","locked":false,"mod_note":null,"mod_reason_by":null,"mod_reason_title":null,"mod_reports":[],"name":"t1_lpmtaix","no_follow":true,"num_reports":null,"parent_id":"t3_1fssvlt","permalink":"/r/macapps/comments/1fssvlt/shottr_18_released/lpmtaix/","removal_reason":null,"replies":"","report_reasons":null,"saved":false,"score":1,"score_hidden":false,"send_replies":true,"stickied":false,"subreddit":"macapps","subreddit_id":"t5_2rt9r","subreddit_name_prefixed":"r/macapps","subreddit_type":"public","top_awarded_type":null,"total_awards_received":0,"treatment_tags":[],"unrepliable_reason":null,"ups":1,"user_reports":[]}],"metadata":{},"error":null}